curl_session/__init__.py
curl_session/curl_session.py
curl_session/kv.py
curl_session/multi_curl.py
curl_session-0.1.18.dist-info/licenses/LICENSE
curl_session-0.1.18.dist-info/METADATA
curl_session-0.1.18.dist-info/WHEEL
curl_session-0.1.18.dist-info/top_level.txt
curl_session-0.1.18.dist-info/RECORD
