Metadata-Version: 2.4
Name: curl-session
Version: 0.1.18
Summary: Initialize from a curl command string and get equivalent requests.Session and httpx.Client objects
Author: Leon
License-Expression: MIT
Classifier: Programming Language :: Python :: 3
Classifier: Operating System :: OS Independent
Requires-Python: >=3.8
License-File: LICENSE
Requires-Dist: requests>=2.31.0
Requires-Dist: httpx[http2]>=0.28.1
Dynamic: license-file
